XStatic_Graphlib-2.1.7.0-py3.6-nspkg.pth
xstatic/pkg/graphlib/__init__.py
xstatic/pkg/graphlib/data/graphlib.core.js
xstatic/pkg/graphlib/data/graphlib.js
XStatic_Graphlib-2.1.7.0.dist-info/METADATA
XStatic_Graphlib-2.1.7.0.dist-info/WHEEL
XStatic_Graphlib-2.1.7.0.dist-info/namespace_packages.txt
XStatic_Graphlib-2.1.7.0.dist-info/top_level.txt
XStatic_Graphlib-2.1.7.0.dist-info/RECORD
