Metadata-Version: 2.1
Name: XStatic-Graphlib
Version: 2.1.7.0
Summary: Graphlib 2.1.7 (XStatic packaging standard)
Home-page: https://github.com/dagrejs/graphlib
Maintainer: Michal Arbet
Maintainer-email: michal.arbet@ultimum.io
License: (same as Graphlib)
Keywords: graphlib xstatic
Platform: any
